MANIFEST.in
README.md
README.txt
setup.cfg
setup.py
django_nagios_cache.egg-info/PKG-INFO
django_nagios_cache.egg-info/SOURCES.txt
django_nagios_cache.egg-info/dependency_links.txt
django_nagios_cache.egg-info/requires.txt
django_nagios_cache.egg-info/top_level.txt
nagios_cache/__init__.py
nagios_cache/admin.py
nagios_cache/apps.py
nagios_cache/models.py
nagios_cache/management/__init__.py
nagios_cache/management/commands/__init__.py
nagios_cache/management/commands/nagios_clean.py
nagios_cache/management/commands/nagios_sync.py
nagios_cache/migrations/0001_initial.py
nagios_cache/migrations/0002_add_constants.py
nagios_cache/migrations/__init__.py