Metadata-Version: 1.1
Name: django-nagios-cache
Version: 0.1.6
Summary: A Django library that sync data from a Nagios/Icinga server.
Home-page: https://github.com/soerenbe/django-nagios-cache
Author: Sören Berger
Author-email: soeren.berger@u1337.de
License: GPL-3
Download-URL: https://github.com/soerenbe/django-nagios-cache/tarball/0.2.0
Keywords: django,nagios,icinga
Platform: UNKNOWN
Classifier: Framework :: Django
Classifier: Intended Audience :: Developers
Classifier: License :: OSI Approved :: GNU General Public License v3 (GPLv3)
